[
  {
    "inputs": [
      {
        "internalType": "uint32",
        "name": "amount",
        "type": "uint32"
      }
    ],
    "name": "deposit",
    "outputs": [],
    "stateMutability": "nonpayable",
    "type": "function"
  },
  {
    "inputs": [
      {
        "internalType": "address",
        "name": "to",
        "type": "address"
      },
      {
        "internalType": "uint32",
        "name": "amount",
        "type": "uint32"
      }
    ],
    "name": "privateTransfer",
    "outputs": [],
    "stateMutability": "nonpayable",
    "type": "function"
  },
  {
    "inputs": [
      {
        "components": [
          {
            "internalType": "address",
            "name": "signer",
            "type": "address"
          },
          {
            "internalType": "bytes",
            "name": "signature",
            "type": "bytes"
          },
          {
            "internalType": "bytes32",
            "name": "publicKey",
            "type": "bytes32"
          }
        ],
        "internalType": "struct Permission",
        "name": "perm",
        "type": "tuple"
      }
    ],
    "name": "getEncryptedBalance",
    "outputs": [
      {
        "internalType": "uint256",
        "name": "",
        "type": "uint256"
      }
    ],
    "stateMutability": "view",
    "type": "function"
  },
  {
    "inputs": [
      {
        "internalType": "uint32",
        "name": "minAmount",
        "type": "uint32"
      },
      {
        "components": [
          {
            "internalType": "address",
            "name": "signer",
            "type": "address"
          },
          {
            "internalType": "bytes",
            "name": "signature",
            "type": "bytes"
          },
          {
            "internalType": "bytes32",
            "name": "publicKey",
            "type": "bytes32"
          }
        ],
        "internalType": "struct Permission",
        "name": "perm",
        "type": "tuple"
      }
    ],
    "name": "hasEnoughBalance",
    "outputs": [
      {
        "internalType": "uint256",
        "name": "",
        "type": "uint256"
      }
    ],
    "stateMutability": "view",
    "type": "function"
  }
]
